metricscores.py
metricscores-0.0.2.dist-info/LICENSE
metricscores-0.0.2.dist-info/METADATA
metricscores-0.0.2.dist-info/WHEEL
metricscores-0.0.2.dist-info/top_level.txt
metricscores-0.0.2.dist-info/RECORD
