Metadata-Version: 2.1
Name: metricscores
Version: 0.0.2
Summary: Description: metrics for regression and classification
Home-page: UNKNOWN
Author: sarath babu
Author-email: babusarath05@gmail.com
License: UNKNOWN
Requires-Dist: sklearn
Requires-Dist: pandas
Requires-Dist: metricscores
